cancan/__init__.py
cancan/ability.py
cancan/rule.py
cancan/tests.py
cancan-0.1.2.dist-info/DESCRIPTION.rst
cancan-0.1.2.dist-info/METADATA
cancan-0.1.2.dist-info/RECORD
cancan-0.1.2.dist-info/WHEEL
cancan-0.1.2.dist-info/metadata.json
cancan-0.1.2.dist-info/top_level.txt
